{"web":{"client_id":"998596709440-4d0uauv9efn96hqq6c3u6ojam8rej21v.apps.googleusercontent.com","project_id":"red-bicicletas-371916","auth_uri":"https://accounts.google.com/o/oauth2/auth","token_uri":"https://oauth2.googleapis.com/token","auth_provider_x509_cert_url":"https://www.googleapis.com/oauth2/v1/certs","client_secret":"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","redirect_uris":["https://red-bicicletas-javi0093.onrender.com/auth/google","https://red-bicicletas-javi0093.onrender.com/auth/google/callback"],"javascript_origins":["https://red-bicicletas-javi0093.onrender.com"]}}